theaddressor/__init__.py
theaddressor/address_parser.py
theaddressor-0.1.2.dist-info/licenses/LICENSE
theaddressor-0.1.2.dist-info/METADATA
theaddressor-0.1.2.dist-info/WHEEL
theaddressor-0.1.2.dist-info/top_level.txt
theaddressor-0.1.2.dist-info/RECORD
