Metadata-Version: 2.4
Name: theaddressor
Version: 0.1.2
Summary: A tool to parse text into structured address data
Author: Charles Watkins
License: BSD-3-Clause
Classifier: Programming Language :: Python :: 3
Classifier: Operating System :: OS Independent
Requires-Python: >=3.7
License-File: LICENSE
Dynamic: license-file
